CHANGELOG.md
LICENSE
MANIFEST.in
README.rst
setup.py
StrangeCase.egg-info/PKG-INFO
StrangeCase.egg-info/SOURCES.txt
StrangeCase.egg-info/dependency_links.txt
StrangeCase.egg-info/entry_points.txt
StrangeCase.egg-info/pbr.json
StrangeCase.egg-info/requires.txt
StrangeCase.egg-info/top_level.txt
strange_case/__init__.py
strange_case/__main__.py
strange_case/config_dict.py
strange_case/processors.py
strange_case/registry.py
strange_case/strange_case_config.py
strange_case/configurators/__init__.py
strange_case/configurators/file_types.py
strange_case/configurators/folder_config_file.py
strange_case/configurators/front_matter_config.py
strange_case/configurators/ignore.py
strange_case/configurators/is_index.py
strange_case/configurators/merge_files_config.py
strange_case/configurators/override.py
strange_case/configurators/page_types.py
strange_case/configurators/set_url.py
strange_case/configurators/setdefault_iterable.py
strange_case/configurators/setdefault_name.py
strange_case/configurators/setdefault_target_name.py
strange_case/configurators/skip_if_not_modified.py
strange_case/extensions/__init__.py
strange_case/extensions/canhaz.py
strange_case/extensions/category.py
strange_case/extensions/clevercss.py
strange_case/extensions/configurator_created_at_from_name.py
strange_case/extensions/configurator_file_stats.py
strange_case/extensions/configurator_order_from_name.py
strange_case/extensions/configurator_strip_extensions.py
strange_case/extensions/configurator_title_from_name.py
strange_case/extensions/configurators.py
strange_case/extensions/date.py
strange_case/extensions/hashlib.py
strange_case/extensions/image.py
strange_case/extensions/inflect.py
strange_case/extensions/markdown.py
strange_case/extensions/misaka.py
strange_case/extensions/paginated.py
strange_case/extensions/scss.py
strange_case/extensions/sha.py
strange_case/extensions/uuid.py
strange_case/nodes/__init__.py
strange_case/nodes/asset.py
strange_case/nodes/file.py
strange_case/nodes/folder.py
strange_case/nodes/jinja.py
strange_case/nodes/node.py
strange_case/nodes/page.py
strange_case/nodes/plywood.py
strange_case/nodes/processor.py
strange_case/nodes/root_folder.py
strange_case/support/__init__.py
