Metadata-Version: 1.2
Name: StrangeCase
Version: 4.6.7
Summary: A straightforward python static site generator.
Home-page: https://github.com/colinta/StrangeCase
Author: Colin T.A. Gray
Author-email: colinta@gmail.com
License: BSD
Keywords: strange_case static site generator
Platform: any
Classifier: Programming Language :: Python
Classifier: Development Status :: 4 - Beta
Classifier: Environment :: Console
Classifier: License :: OSI Approved :: BSD License
Classifier: Operating System :: OS Independent
Classifier: Intended Audience :: End Users/Desktop
Classifier: Intended Audience :: Developers
Classifier: Intended Audience :: System Administrators
Classifier: Topic :: Text Processing
Classifier: Topic :: Software Development
Classifier: Topic :: Software Development :: Build Tools
Classifier: Topic :: Software Development :: Code Generators
Classifier: Topic :: Internet
Classifier: Topic :: Internet :: WWW/HTTP :: Site Management
Requires-Python: >3.0.0
